gpt_shell/__init__.py
gpt_shell/cli.py
gpt_shell/config.py
gpt_shell/core.py
gpt_shell/llm_client.py
gpt_shell/llm_manager.py
gpt_shell/main.py
gpt_shell/py.typed
gpt_shell/utils.py
llmshell_cli-0.0.1.dist-info/licenses/LICENSE
llmshell_cli-0.0.1.dist-info/METADATA
llmshell_cli-0.0.1.dist-info/WHEEL
llmshell_cli-0.0.1.dist-info/entry_points.txt
llmshell_cli-0.0.1.dist-info/top_level.txt
llmshell_cli-0.0.1.dist-info/RECORD
