Metadata-Version: 2.4
Name: llmshell-cli
Version: 0.0.1
Summary: Convert natural language to shell commands using LLMs (GPT4All, OpenAI, Ollama)
Author-email: Naresh Reddy Gurijala <naresh.gurijala@gmail.com>
Maintainer-email: Naresh Reddy Gurijala <naresh.gurijala@gmail.com>
License: MIT
Project-URL: Homepage, https://github.com/imgnr/llmshell
Project-URL: Repository, https://github.com/imgnr/llmshell
Project-URL: Issues, https://github.com/imgnr/llmshell/issues
Keywords: gpt,shell,cli,llm,gpt4all,openai,ollama,command-line,natural-language,aishell,intelligent-shell
Classifier: Development Status :: 3 - Alpha
Classifier: Intended Audience :: Developers
Classifier: License :: OSI Approved :: MIT License
Classifier: Programming Language :: Python :: 3
Classifier: Programming Language :: Python :: 3.8
Classifier: Programming Language :: Python :: 3.9
Classifier: Programming Language :: Python :: 3.10
Classifier: Programming Language :: Python :: 3.11
Classifier: Programming Language :: Python :: 3.12
Requires-Python: >=3.8
License-File: LICENSE
Requires-Dist: typer>=0.9.0
Requires-Dist: pyyaml>=6.0
Requires-Dist: gpt4all>=2.0.0
Requires-Dist: requests>=2.31.0
Requires-Dist: rich>=13.0.0
Requires-Dist: openai>=1.0.0
Provides-Extra: dev
Requires-Dist: pytest>=7.0; extra == "dev"
Requires-Dist: pytest-cov>=4.0; extra == "dev"
Requires-Dist: black>=23.0; extra == "dev"
Requires-Dist: flake8>=6.0; extra == "dev"
Requires-Dist: mypy>=1.0; extra == "dev"
Dynamic: license-file
